libname/__init__.py
libname/main.py
pncrypto-0.0.4.dist-info/METADATA
pncrypto-0.0.4.dist-info/WHEEL
pncrypto-0.0.4.dist-info/entry_points.txt
pncrypto-0.0.4.dist-info/top_level.txt
pncrypto-0.0.4.dist-info/RECORD
