Metadata-Version: 2.1
Name: pncrypto
Version: 0.0.4
Summary: Streaming video data via networks
Author: (Glorian Dedov)
Author-email: <darthunadmired@gmail.com>
Keywords: python,video,stream,video stream,camera stream,sockets
Classifier: Development Status :: 1 - Planning
Classifier: Intended Audience :: Developers
Classifier: Programming Language :: Python :: 3
Classifier: Operating System :: Unix
Classifier: Operating System :: MacOS :: MacOS X
Classifier: Operating System :: Microsoft :: Windows
